anansi/__init__.py
anansi/client.py
anansi_compute-0.1.0.dist-info/METADATA
anansi_compute-0.1.0.dist-info/WHEEL
anansi_compute-0.1.0.dist-info/top_level.txt
anansi_compute-0.1.0.dist-info/RECORD
