Metadata-Version: 2.4
Name: anansi-compute
Version: 0.1.0
Summary: Secure multi-cloud compute orchestration with TEE and GPU CC support
Author-email: Rewsr <hello@rewsr.com>
License: MIT
Project-URL: Homepage, https://rewsr.com
Project-URL: Documentation, https://docs.rewsr.com
Project-URL: Repository, https://github.com/rewsr/anansi-compute
Project-URL: Issues, https://github.com/rewsr/anansi-compute/issues
Keywords: confidential-computing,tee,gpu,multi-cloud,secure-compute
Classifier: Development Status :: 4 - Beta
Classifier: Intended Audience :: Developers
Classifier: License :: OSI Approved :: MIT License
Classifier: Programming Language :: Python :: 3
Classifier: Programming Language :: Python :: 3.7
Classifier: Programming Language :: Python :: 3.8
Classifier: Programming Language :: Python :: 3.9
Classifier: Programming Language :: Python :: 3.10
Classifier: Programming Language :: Python :: 3.11
Classifier: Topic :: Security :: Cryptography
Classifier: Topic :: System :: Distributed Computing
Requires-Python: >=3.7
Requires-Dist: requests>=2.25.0
Requires-Dist: typing-extensions>=3.7.4
Provides-Extra: dev
Requires-Dist: pytest>=6.0; extra == "dev"
Requires-Dist: black; extra == "dev"
Requires-Dist: flake8; extra == "dev"
